octogen/py.typed
octogen/shop_agent/__init__.py
octogen/shop_agent/base.py
octogen/shop_agent/checkpointer.py
octogen/shop_agent/crud.py
octogen/shop_agent/factory.py
octogen/shop_agent/py.typed
octogen/shop_agent/schemas.py
octogen/shop_agent/server.py
octogen/shop_agent/settings.py
octogen/shop_agent/utils.py
octogen_sdk_langgraph-0.1.9.dist-info/METADATA
octogen_sdk_langgraph-0.1.9.dist-info/WHEEL
octogen_sdk_langgraph-0.1.9.dist-info/licenses/LICENSE
octogen_sdk_langgraph-0.1.9.dist-info/RECORD
