Metadata-Version: 2.4
Name: octogen-sdk-langgraph
Version: 0.1.9
Summary: Octogen Python SDK built on langgraph
Project-URL: Homepage, https://octogen.ai
Project-URL: Issues, https://github.com/octogen-systems/octogen-py-sdk/issues
License-Expression: MIT
License-File: LICENSE
Classifier: Operating System :: OS Independent
Classifier: Programming Language :: Python :: 3
Classifier: Programming Language :: Python :: 3.12
Requires-Python: >=3.12
Requires-Dist: fastapi>=0.115.14
Requires-Dist: jsonpatch>=1.33
Requires-Dist: langchain-mcp-adapters>=0.1.8
Requires-Dist: langchain-openai>=0.3.27
Requires-Dist: langchain-openapi>=0.1.1
Requires-Dist: langchain>=0.3.25
Requires-Dist: langgraph>=0.4.3
Requires-Dist: mcp>=1.10.1
Requires-Dist: octogen-api>=0.1.0a8
Requires-Dist: pydantic-settings>=2.9.1
Requires-Dist: pydantic>=2.11.4
Requires-Dist: python-dotenv>=1.1.0
Requires-Dist: ruff>=0.11.10
Requires-Dist: structlog>=25.3.0
Requires-Dist: uvicorn>=0.35.0
